exbetapi/__init__.py
exbetapi/api.py
exbetapi/cli.py
exbetapi/exceptions.py
exbetapi-2.4.1.dist-info/METADATA
exbetapi-2.4.1.dist-info/WHEEL
exbetapi-2.4.1.dist-info/entry_points.txt
exbetapi-2.4.1.dist-info/RECORD
