Metadata-Version: 2.1
Name: exbetapi
Version: 2.4.1
Summary: Python Bindings for Trading API for exbet.io
Home-page: https://github.com/exbet/python-exbetapi
Author: Python Development Team
Author-email: py@exbet.io
Requires-Python: >=3.6,<4.0
Classifier: Programming Language :: Python :: 3
Classifier: Programming Language :: Python :: 3.6
Classifier: Programming Language :: Python :: 3.7
Classifier: Programming Language :: Python :: 3.8
Classifier: Programming Language :: Python :: 3.9
Classifier: Programming Language :: Python :: 3.10
Classifier: Programming Language :: Python :: 3.11
Requires-Dist: requests (>=2.22.0,<3.0.0)
Project-URL: Bug Tracker, https://github.com/exbet/python-exbetapi/issues
Project-URL: Documentation, https://python-exbetapi.rtfd.io
Project-URL: Repository, https://github.com/exbet/python-exbetapi
